sklearne/__init__.py
sklearne/loader.py
sklearne/data/A1.txt
sklearne/data/A2.txt
sklearne/data/A3.txt
sklearne/data/A4.txt
sklearne/data/A5.txt
sklearne/data/B1.txt
sklearne/data/B2.txt
sklearne/data/B4.txt
sklearne/data/B6.txt
sklearne/data/B7.txt
sklearne-1.0.dist-info/METADATA
sklearne-1.0.dist-info/WHEEL
sklearne-1.0.dist-info/top_level.txt
sklearne-1.0.dist-info/RECORD
