Metadata-Version: 2.1
Name: sklearne
Version: 1.0
Summary: Saver
Author: Your Name
